{
    "wp": [
        {
            "dist_cm": 5,
            "dist_px": 111,
            "angle_deg": 2
        },
        {
            "dist_cm": 58,
            "dist_px": 3,
            "angle_deg": 95
        },
        {
            "dist_cm": 3,
            "dist_px": 91,
            "angle_deg": 88
        }
    ],
    "pos": [
        [
            162,
            242
        ],
        [
            167,
            131
        ],
        [
            225,
            128
        ],
        [
            228,
            219
        ]
    ]
}